data/test_vectors.json
docs/conf.py
docs/source/conf.py
kha256/__init__.py
kha256/_version.py
kha256/kha256.py
kha256-0.1.3.dist-info/licenses/LICENSE
tests/test_sample.py
kha256-0.1.3.dist-info/METADATA
kha256-0.1.3.dist-info/WHEEL
kha256-0.1.3.dist-info/top_level.txt
kha256-0.1.3.dist-info/RECORD
