Metadata-Version: 2.4
Name: kha256
Version: 0.1.3
Summary: Keçeci Hash Algorithm (Keçeci Hash Algoritması), KHA-256
Home-page: https://github.com/WhiteSymmetry/kha256
Author: Mehmet Keçeci
Author-email: Mehmet Keçeci <mkececi@yaani.com>
Maintainer: Mehmet Keçeci
Maintainer-email: mkececi@yaani.com
License:                     GNU AFFERO GENERAL PUBLIC LICENSE
Project-URL: Homepage, https://github.com/WhiteSymmetry/kha256
Project-URL: Repository, https://github.com/WhiteSymmetry/kha256
Classifier: Programming Language :: Python :: 3
Classifier: Operating System :: OS Independent
Classifier: Intended Audience :: Science/Research
Classifier: Topic :: Scientific/Engineering :: Visualization
Requires-Python: >=3.11
License-File: LICENSE
Requires-Dist: numpy
Requires-Dist: kececinumbers
Provides-Extra: test
Requires-Dist: pytest; extra == "test"
Requires-Dist: pytest-cov; extra == "test"
Requires-Dist: pytest-mock; extra == "test"
Requires-Dist: ruff; extra == "test"
Dynamic: author
Dynamic: home-page
Dynamic: license-file
Dynamic: maintainer
Dynamic: maintainer-email
Dynamic: requires-python
